claude_agent_api/__init__.py
claude_agent_api/cli.py
claude_agent_api/client.py
claude_agent_api/config.py
claude_agent_api/models.py
claude_agent_api/schema.py
claude_agent_api/server.py
claude_agent_api-0.1.0.dist-info/METADATA
claude_agent_api-0.1.0.dist-info/WHEEL
claude_agent_api-0.1.0.dist-info/entry_points.txt
claude_agent_api-0.1.0.dist-info/RECORD
