Metadata-Version: 2.4
Name: claude-agent-api
Version: 0.1.0
Summary: Python client for Claude Agent API
Requires-Python: >=3.13
Requires-Dist: anyio>=4.8.0
Requires-Dist: claude-agent-sdk>=0.1.19
Requires-Dist: fastapi>=0.115.6
Requires-Dist: pydantic>=2.10.5
Requires-Dist: strawberry-graphql[fastapi]>=0.253.3
Requires-Dist: uvicorn[standard]>=0.34.0
